{
  "Name": "CEP LATAM Developer",
  "IsCustom": true,
  "Description": "Developers on the CEP Latam project",
  "Actions": [
    "Microsoft.Resources/subscriptions/read",
    "Microsoft.Cache/redis/*",
    "Microsoft.Authorization/*/read",
    "Microsoft.Insights/alertRules/*",
    "Microsoft.ResourceHealth/availabilityStatuses/read",
    "Microsoft.Resources/deployments/*",
    "Microsoft.Resources/subscriptions/resourceGroups/read",
    "Microsoft.Support/*"
  ],
  "DataActions": [
  ],
  "NotDataActions": [
  ],
  "AssignableScopes": [ "/" ]
}
